aliyun/trace/aliyun_llm_trace.py
aliyun/trace/version.py
aliyun/trace/entities/arms_llm_trace_entity.py
aliyun/trace/utils/__init__.py
aliyun_trace-1.0.3.dist-info/METADATA
aliyun_trace-1.0.3.dist-info/WHEEL
aliyun_trace-1.0.3.dist-info/RECORD
